holo/__init__.py
holo/logging/__init__.py
holo/logging/_wandb_setup.py
holo/optim/__init__.py
holo/optim/_discrete_evolution.py
holo/test_functions/__init__.py
holo/test_functions/closed_form/__init__.py
holo/test_functions/closed_form/_ehrlich.py
holo/test_functions/closed_form/_rough_mt_fuji.py
holo/test_functions/elemental/__init__.py
holo/test_functions/elemental/_discrete_markov_process.py
holo/test_functions/elemental/_hamming_dist.py
holo/test_functions/elemental/_motif.py
holo/test_functions/lookup/__init__.py
holo/test_functions/lookup/_abstract_lookup.py
holo/test_functions/lookup/_dhfr.py
holo/test_functions/lookup/_tfbind8.py
holo/test_functions/lookup/_trpb.py
pytorch_holo-0.0.5.dist-info/licenses/LICENSE
pytorch_holo-0.0.5.dist-info/METADATA
pytorch_holo-0.0.5.dist-info/WHEEL
pytorch_holo-0.0.5.dist-info/top_level.txt
pytorch_holo-0.0.5.dist-info/RECORD
